MANIFEST.in
README.rst
nose_sphinx_doc.py
setup.cfg
setup.py
nose_sphinx_doc.egg-info/PKG-INFO
nose_sphinx_doc.egg-info/SOURCES.txt
nose_sphinx_doc.egg-info/dependency_links.txt
nose_sphinx_doc.egg-info/entry_points.txt
nose_sphinx_doc.egg-info/not-zip-safe
nose_sphinx_doc.egg-info/requires.txt
nose_sphinx_doc.egg-info/top_level.txt
tests/__init__.py
tests/__init__.pyc
tests/test_functional.py
tests/test_functional.pyc
tests/test_unit.py
tests/test_unit.pyc