Metadata-Version: 1.0
Name: nose-sphinx-doc
Version: 0.1
Summary: Generate sphinx documentation for tests.
Home-page: http://github.com/Fiedzia/NoseSphinxDoc
Author: Maciej Dziardziel
Author-email: fiedzia@gmail.com
License: GNU LGPL
Platform: UNKNOWN
Classifier: Development Status :: 3 - Alpha
Classifier: Intended Audience :: Developers
Classifier: License :: OSI Approved :: GNU Library or Lesser General Public License (LGPL)
Classifier: Topic :: Software Development :: Testing
Classifier: Programming Language :: Python
